stereoscopy/__init__.py
stereoscopy/__main__.py
stereoscopy-2.0.1.dist-info/LICENCE
stereoscopy-2.0.1.dist-info/METADATA
stereoscopy-2.0.1.dist-info/WHEEL
stereoscopy-2.0.1.dist-info/entry_points.txt
stereoscopy-2.0.1.dist-info/top_level.txt
stereoscopy-2.0.1.dist-info/RECORD
