Metadata-Version: 2.1
Name: stereoscopy
Version: 2.0.1
Summary: StereoscoPy, stereoscopic 3D image creator
Home-page: https://github.com/2sh/StereoscoPy
Author: Seán Hewitt
Author-email: contact@2sh.me
License: UNKNOWN
Platform: UNKNOWN
Classifier: Programming Language :: Python :: 2
Classifier: Programming Language :: Python :: 2.7
Classifier: Programming Language :: Python :: 3
Classifier: Programming Language :: Python :: 3.4
Classifier: Programming Language :: Python :: 3.5
Classifier: Programming Language :: Python :: 3.6
Classifier: Programming Language :: Python :: 3.7
Classifier: License :: OSI Approved :: GNU General Public License v3 or later (GPLv3+)
Classifier: Operating System :: OS Independent
Classifier: Topic :: Multimedia :: Graphics
Requires-Python: >=2.7,!=3.0.*,!=3.1.*,!=3.2.*,!=3.3.*
Requires-Dist: Pillow
Provides-Extra: auto_align
Requires-Dist: opencv-python ; extra == 'auto_align'
Requires-Dist: numpy ; extra == 'auto_align'
